aiofmp/__init__.py
aiofmp/analyst.py
aiofmp/analyst_tools.py
aiofmp/base.py
aiofmp/calendar.py
aiofmp/calendar_tools.py
aiofmp/chart.py
aiofmp/chart_tools.py
aiofmp/cli.py
aiofmp/commodity.py
aiofmp/commodity_tools.py
aiofmp/company.py
aiofmp/company_tools.py
aiofmp/cot.py
aiofmp/cot_tools.py
aiofmp/crypto.py
aiofmp/crypto_tools.py
aiofmp/dcf.py
aiofmp/dcf_tools.py
aiofmp/directory.py
aiofmp/directory_tools.py
aiofmp/economics.py
aiofmp/economics_tools.py
aiofmp/etf.py
aiofmp/etf_tools.py
aiofmp/fmp_client.py
aiofmp/forex.py
aiofmp/forex_tools.py
aiofmp/form13f.py
aiofmp/form13f_tools.py
aiofmp/indexes.py
aiofmp/indexes_tools.py
aiofmp/insider_trades.py
aiofmp/insider_trades_tools.py
aiofmp/market_performance.py
aiofmp/market_performance_tools.py
aiofmp/mcp_server.py
aiofmp/mcp_tools.py
aiofmp/news.py
aiofmp/news_tools.py
aiofmp/quote.py
aiofmp/quote_tools.py
aiofmp/search.py
aiofmp/search_tools.py
aiofmp/senate.py
aiofmp/senate_tools.py
aiofmp/statements.py
aiofmp/statements_tools.py
aiofmp/technical_indicators.py
aiofmp/technical_indicators_tools.py
aiofmp-1.0.0.dist-info/METADATA
aiofmp-1.0.0.dist-info/WHEEL
aiofmp-1.0.0.dist-info/entry_points.txt
aiofmp-1.0.0.dist-info/licenses/LICENSE
aiofmp-1.0.0.dist-info/RECORD
