Metadata-Version: 2.4
Name: aiofmp
Version: 1.0.0
Summary: Asynchronous Financial Modeling Prep API Client with MCP Server
Project-URL: Homepage, https://github.com/codemug/aiofmp
Project-URL: Documentation, https://github.com/codemug/aiofmp#readme
Project-URL: Repository, https://github.com/codemug/aiofmp.git
Project-URL: Issues, https://github.com/codemug/aiofmp/issues
Author-email: codemug <u.manshahid@gmail.com>
Maintainer-email: codemug <u.manshahid@gmail.com>
License: Apache 2.0
License-File: LICENSE
Keywords: api,async,crypto,financial,financial-modeling-prep,forex,mcp,model-context-protocol,stocks
Classifier: Development Status :: 4 - Beta
Classifier: Intended Audience :: Developers
Classifier: Intended Audience :: Financial and Insurance Industry
Classifier: Operating System :: OS Independent
Classifier: Programming Language :: Python :: 3
Classifier: Programming Language :: Python :: 3.10
Classifier: Programming Language :: Python :: 3.11
Classifier: Programming Language :: Python :: 3.12
Classifier: Programming Language :: Python :: 3.13
Classifier: Topic :: Internet :: WWW/HTTP :: Dynamic Content
Classifier: Topic :: Office/Business :: Financial :: Investment
Classifier: Topic :: Software Development :: Libraries :: Python Modules
Classifier: Typing :: Typed
Requires-Python: >=3.10
Requires-Dist: aiohttp>=3.12.15
Requires-Dist: click>=8.0.0
Requires-Dist: fastmcp>=2.0.0
Requires-Dist: pytest-asyncio>=1.1.0
Requires-Dist: pytest-cov>=5.0.0
Requires-Dist: pytest>=8.4.1
Requires-Dist: ruff>=0.13.2
Provides-Extra: dev
Requires-Dist: black>=25.0.0; extra == 'dev'
Requires-Dist: isort>=6.0.0; extra == 'dev'
Requires-Dist: mypy>=1.18.0; extra == 'dev'
Requires-Dist: pytest-asyncio>=1.2.0; extra == 'dev'
Requires-Dist: pytest-cov>=7.0.0; extra == 'dev'
Requires-Dist: pytest-mock>=3.15.0; extra == 'dev'
Requires-Dist: pytest>=8.4.1; extra == 'dev'
Requires-Dist: python-semantic-release>=10.4.1; extra == 'dev'
Requires-Dist: ruff>=0.13.0; extra == 'dev'
Requires-Dist: twine>=5.0.0; extra == 'dev'
